pythonvideoannotator_models/__init__.py
pythonvideoannotator_models/models/__init__.py
pythonvideoannotator_models/models/imodel.py
pythonvideoannotator_models/models/project_base.py
pythonvideoannotator_models/models/project_io.py
pythonvideoannotator_models/models/video/__init__.py
pythonvideoannotator_models/models/video/video_base.py
pythonvideoannotator_models/models/video/video_io.py
pythonvideoannotator_models/models/video/objects/__init__.py
pythonvideoannotator_models/models/video/objects/video_object.py
pythonvideoannotator_models/models/video/objects/geometry/__init__.py
pythonvideoannotator_models/models/video/objects/geometry/geometry_base.py
pythonvideoannotator_models/models/video/objects/geometry/geometry_io.py
pythonvideoannotator_models/models/video/objects/image/__init__.py
pythonvideoannotator_models/models/video/objects/image/image_base.py
pythonvideoannotator_models/models/video/objects/image/image_io.py
pythonvideoannotator_models/models/video/objects/note/__init__.py
pythonvideoannotator_models/models/video/objects/note/note_base.py
pythonvideoannotator_models/models/video/objects/note/note_io.py
pythonvideoannotator_models/models/video/objects/object2d/__init__.py
pythonvideoannotator_models/models/video/objects/object2d/object2d_base.py
pythonvideoannotator_models/models/video/objects/object2d/object2d_io.py
pythonvideoannotator_models/models/video/objects/object2d/datasets/__init__.py
pythonvideoannotator_models/models/video/objects/object2d/datasets/dataset.py
pythonvideoannotator_models/models/video/objects/object2d/datasets/contours/__init__.py
pythonvideoannotator_models/models/video/objects/object2d/datasets/contours/contours_base.py
pythonvideoannotator_models/models/video/objects/object2d/datasets/contours/contours_io.py
pythonvideoannotator_models/models/video/objects/object2d/datasets/path/__init__.py
pythonvideoannotator_models/models/video/objects/object2d/datasets/path/path_base.py
Python_video_annotator_models_shaliulab-0.9.0.dist-info/METADATA
Python_video_annotator_models_shaliulab-0.9.0.dist-info/WHEEL
Python_video_annotator_models_shaliulab-0.9.0.dist-info/top_level.txt
Python_video_annotator_models_shaliulab-0.9.0.dist-info/RECORD
